MANIFEST.in
README.md
setup.py
smartstream/__init__.py
smartstream/blocks.py
smartstream/edit_handlers.py
smartstream/static/smartstream/js/list.js
smartstream/static/smartstream/js/stream.js
wagtail_smartstream.egg-info/PKG-INFO
wagtail_smartstream.egg-info/SOURCES.txt
wagtail_smartstream.egg-info/dependency_links.txt
wagtail_smartstream.egg-info/not-zip-safe
wagtail_smartstream.egg-info/top_level.txt