Metadata-Version: 1.1
Name: wagtail-smartstream
Version: 0.1
Summary: Proof of concept Wagtail StreamFieldPanel that avoids unnecessary template rendering.
Home-page: https://github.com/inueni/wagtail-smartstream/
Author: Mitja Pagon
Author-email: mitja@inueni.com
License: MIT
Keywords: w,a,g,t,a,i,l, ,a,d,m,i,n, ,s,t,r,e,a,m,f,i,e,l,d, ,d,j,a,n,g,o, ,c,m,s
Platform: UNKNOWN
Classifier: Development Status :: 4 - Beta
Classifier: Environment :: Web Environment
Classifier: Intended Audience :: Developers
Classifier: Operating System :: OS Independent
Classifier: License :: OSI Approved :: MIT License
Classifier: Topic :: Software Development :: Libraries :: Python Modules
Classifier: Programming Language :: Python
Classifier: Programming Language :: Python :: 2
Classifier: Programming Language :: Python :: 2.7
Classifier: Programming Language :: Python :: 3
Classifier: Programming Language :: Python :: 3.4
Classifier: Programming Language :: Python :: 3.5
Classifier: Programming Language :: Python :: 3.6
Classifier: Framework :: Django
Classifier: Framework :: Django :: 1.9
Classifier: Framework :: Django :: 1.10
Classifier: Framework :: Django :: 1.11
